verifyshopify/__init__.py
verifyshopify/verify.py
shopify_webhook_verification-0.1.0.dist-info/METADATA
shopify_webhook_verification-0.1.0.dist-info/WHEEL
shopify_webhook_verification-0.1.0.dist-info/RECORD
